pyodide_pack/__init__.py
pyodide_pack/_utils.py
pyodide_pack/archive.py
pyodide_pack/cli.py
pyodide_pack/dynamic_lib.py
pyodide_pack/runners/__init__.py
pyodide_pack/runners/node.py
pyodide_pack/tests/__init__.py
pyodide_pack/tests/test_archive.py
pyodide_pack/tests/test_cli.py
pyodide_pack-0.2.0.dist-info/LICENSE
pyodide_pack-0.2.0.dist-info/METADATA
pyodide_pack-0.2.0.dist-info/WHEEL
pyodide_pack-0.2.0.dist-info/entry_points.txt
pyodide_pack-0.2.0.dist-info/top_level.txt
pyodide_pack-0.2.0.dist-info/RECORD
