Metadata-Version: 2.1
Name: pyodide-pack
Version: 0.2.0
Summary: A bundler for Python packages for the web
Home-page: https://github.com/rth/pyodide-bundler
Author: Roman Yurchak
Project-URL: Bug Tracker, https://github.com/rth/pyodide-bundler
Classifier: Programming Language :: Python :: 3
Classifier: License :: OSI Approved :: Mozilla Public License 2.0 (MPL 2.0)
Classifier: Operating System :: OS Independent
Requires-Python: >=3.9
License-File: LICENSE
Requires-Dist: typer (~=0.4.1)
Requires-Dist: rich (~=12.3.0)
Requires-Dist: jinja2 (~=3.1.2)
Requires-Dist: pyodide-cli (>=0.2.0)
